README.md
setup.py
example_pkg/__init__.py
example_pkg_sbedi.egg-info/PKG-INFO
example_pkg_sbedi.egg-info/SOURCES.txt
example_pkg_sbedi.egg-info/dependency_links.txt
example_pkg_sbedi.egg-info/requires.txt
example_pkg_sbedi.egg-info/top_level.txt