Metadata-Version: 2.1
Name: example-pkg-sbedi
Version: 0.0.1
Summary: A small example package
Home-page: UNKNOWN
Author: Example Author
Author-email: author@example.com
License: UNKNOWN
Platform: UNKNOWN
Classifier: Programming Language :: Python :: 2.7
Classifier: License :: OSI Approved :: MIT License
Classifier: Operating System :: OS Independent
